llmfsd/__init__.py
llmfsd/data_model.py
llmfsd/faker.py
llmfsd/parser.py
llmfsd/prompt.py
llmfsd-0.1.3.dist-info/METADATA
llmfsd-0.1.3.dist-info/WHEEL
llmfsd-0.1.3.dist-info/RECORD
