Metadata-Version: 2.1
Name: llmfsd
Version: 0.1.3
Summary: llmfsd: LLM Fake Structured Data, faking Structured Data from any LLM
Author: Donatien YETO
Author-email: donatien.yeto@dinyad.fr
Requires-Python: >=3.10,<4.0
Classifier: Programming Language :: Python :: 3
Classifier: Programming Language :: Python :: 3.10
Classifier: Programming Language :: Python :: 3.11
Classifier: Programming Language :: Python :: 3.12
Classifier: Programming Language :: Python :: 3.13
Provides-Extra: all
Provides-Extra: anthropic
Provides-Extra: aws
Provides-Extra: google
Provides-Extra: groq
Provides-Extra: mistral
Provides-Extra: openai
Requires-Dist: aisuite (>=0.1.6,<0.2.0)
Requires-Dist: anthropic (>=0.30.1,<0.31.0) ; extra == "all" or extra == "anthropic"
Requires-Dist: boto3 (>=1.34.144,<2.0.0) ; extra == "aws"
Requires-Dist: groq (>=0.9.0,<0.10.0) ; extra == "all" or extra == "groq"
Requires-Dist: mistralai (>=1.2.3,<2.0.0) ; extra == "mistral"
Requires-Dist: openai (>=1.35.8,<2.0.0) ; extra == "all" or extra == "openai"
Requires-Dist: python-dotenv (>=1.0.1,<2.0.0)
Requires-Dist: vertexai (>=1.63.0,<2.0.0) ; extra == "google"
